{
  "ハル": {
    "correct": false,
    "goodPoints": [
      "望遠鏡での観察記録が詳しく、色の違いをちゃんと見分けていたのは素晴らしいね"
    ],
    "missedClues": [
      "書きかえの時刻を特定するには、20:00のデータとの「ずれ」を計算してみよう",
      "3か所全部が同じ方向に約45度ずれているよ。星は1時間に15度動くことを思い出そう"
    ],
    "hint": "45度のずれは何時間分の星の動き？1時間15度で計算してみよう"
  },
  "ヒカル": {
    "correct": true,
    "goodPoints": [
      "コンクール前に「もう一度確認したい」と行動した姿勢を見抜けたね",
      "時刻の違いによる星の動きの誤解が原因だと気づけたのは見事！"
    ],
    "missedClues": [],
    "hint": "23:00の空と20:00のデータでは時刻が違う。地球が自転しているから1時間で約15度も星が動いて見えるんだよ"
  },
  "ソラ": {
    "correct": false,
    "goodPoints": [
      "20:00の正確なデータを記録用紙に残していたのは真相を明かすカギだったね"
    ],
    "missedClues": [
      "書きかえ後のデータが何時の空に合わせてあるか、時間で計算してみよう",
      "自分の記録と書きかえ後のずれを星の動きのルールで計算すると23:00の行動が浮かぶよ"
    ],
    "hint": "書きかえ前後のデータのずれを1時間15度のルールで計算してみよう"
  },
  "ツキ": {
    "correct": false,
    "goodPoints": [
      "20:00のスケッチが正確でデータの信頼性を証明してくれたね"
    ],
    "missedClues": [
      "22:30にある人物が外に出ていくのを見た情報が推理の決め手になるよ",
      "友達を守りたい気持ちは分かるけど、事実は事実だよ"
    ],
    "hint": "見たのはある人物が外に出ていくこと。それだけで行動と書きかえのタイミングが重なるよ"
  }
}