{
  "title": "消えたゴールドスターと4つのアリバイ",
  "fullTitle": "ナゾトキ探偵団 数字の迷宮 Vol.1「消えたゴールドスターと4つのアリバイ」",
  "series": "math",
  "seriesName": "数字の迷宮",
  "seriesOrder": 4,
  "volume": 1,
  "slug": "math-01-alibi-amusement",
  "subject": "算数（速さ×時間＝距離）",
  "players": "2〜4人（親子推奨: 親1+子1〜2、または子ども同士3〜4人）",
  "age": "小学5年〜小学6年（速さの単元を学習済みが望ましい）",
  "time": "30〜45分",
  "difficulty": "★★☆（初心者OK。計算用にメモ用紙とえんぴつ必須）",
  "synopsis": "ワクワク遊園地の「探偵フェスティバル」開催中。会場のシンボル「ゴールドスター・トロフィー」が事務所から消えた。トロフィーが消えたのは13:50〜14:20の間（約30分間）。4人のスタッフ全員が「自分はその時間、別の場所にいた」と主張する。しかし目撃証言によると、全員に「いなかった時間」がある——。プレイヤーたちは遊園地の地図と各スタッフの歩く速さを使い、計算でアリバイを検証し、犯人を突き止める。",
  "truth": "犯人は**カケダシ**（遊園地のアルバイト少年）。\n\n#### アリバイ崩しの計算\n\n各容疑者について「持ち場→事務所→持ち場」の往復時間を計算し、空白時間と比較する。\n\n| 容疑者 | 持ち場（事務所からの距離） | 歩く速さ | 空白時間 | 往復距離 | 往復にかかる時間 | 犯行可能？ |\n|---|---|---|---|---|---|---|\n| ハヤアシ | ジェットコースター（300m） | 100m/分 | 5分 | 600m | 600÷100＝**6分** | ✕（6分＞5分）|\n| ノンビリ | 観覧車（200m） | 50m/分 | 6分 | 400m | 400÷50＝**8分** | ✕（8分＞6分）|\n| カケダシ | お化け屋敷（500m） | 100m/分 | 20分 | 1000m | 1000÷100＝**10分** | **◯（10分＜20分）** |\n| マモル | フードコート（400m） | 100m/分 | 7分 | 800m | 800÷100＝**8分** | ✕（8分＞7分）|\n\n**カケダシだけが、空白時間（20分）の中で事務所を往復（10分）し、犯行（約10分）を行える。**\n\n#### カケダシの犯行タイムライン\n- 13:55 お化け屋敷を出る\n- 14:00 事務所に到着（500m÷100m/分＝5分）\n- 14:00〜14:10 トロフィーを持ち出し、包んで運ぶ（10分）\n- 14:10 事務所を出発\n- 14:15 お化け屋敷に帰還（500m÷100m/分＝5分）\n\n#### カケダシの動機\nワンダー園長が「古いゴールドスターは来月処分して、新品に交換する」と言っていた。ゴールドスターは園長の亡くなったお父さん（遊園地の創設者）が手作りした思い出の品。カケダシは子どもの頃にその話を創設者本人から聞いていて、捨てられるのが許せなかった。だからお化け屋敷の秘密の部屋に隠した。",
  "learningGoals": "1. 「速さ×時間＝距離」の公式を実践的に使う\n2. 距離÷速さ＝時間の計算でアリバイを検証する\n3. 複数の情報を整理し、比較して結論を出す力（論理的思考）\n4. 「計算で事実を証明する」体験から、算数の実用性を感じる",
  "common": "# ナゾトキ探偵団 数字の迷宮 Vol.1「消えたゴールドスターと4つのアリバイ」\r\n\r\n## 〜 みんなに読んでもらう情報 〜\r\n\r\n---\r\n\r\n### きみたちは「ナゾトキ{探偵団|たんていだん}」だ！\r\n\r\nきみたちはワクワク遊園地の「探偵フェスティバル」に遊びに来た。\r\n入口に大きなポスターが{貼|は}ってある。\r\n\r\n> 「探偵フェスティバル開催中！\r\n> 　園内で起きたナゾを解いて、{名探偵|めいたんてい}になろう！\r\n> 　——ワクワク遊園地 ワンダー{園長|えんちょう}」\r\n\r\nすると{突然|とつぜん}、園内放送が流れた。\r\n\r\n> 「大変だ〜！ ゴールドスター・トロフィーが{事務所|じむしょ}から消えた！\r\n> 　探偵フェスティバルのみなさん、これは{本物|ほんもの}の事件です！\r\n> 　{犯人|はんにん}を見つけてください！ ——ワンダー園長」\r\n\r\n---\r\n\r\n### {舞台|ぶたい}：ワクワク遊園地\r\n\r\nワクワク遊園地は、30年前に「ワンダーじいちゃん」が作った遊園地。\r\n今は{息子|むすこ}のワンダー園長が引き{継|つ}いでいる。\r\n\r\n遊園地のシンボルは**「ゴールドスター・トロフィー」**——\r\nワンダーじいちゃんが自分の手で作った、金色に{輝|かがや}く星の形のトロフィーだ。\r\n\r\n---\r\n\r\n### ★遊園地の地図★（{超重要|ちょうじゅうよう}！！ 計算に使うよ！）\r\n\r\n```\r\n                [ジェットコースター]\r\n                       |\r\n                     300m\r\n                       |\r\n[{観覧車|かんらんしゃ}]--200m--[★{事務所|じむしょ}]--400m--[フードコート]\r\n                       |\r\n                     500m\r\n                       |\r\n                [お化け{屋敷|やしき}]\r\n```\r\n\r\n**★ 道は{十字|じゅうじ}の形！ どこに行くにも事務所を通る！ ★**\r\n\r\n| 場所 | 事務所からの{距離|きょり} |\r\n|---|---|\r\n| ジェットコースター（{北|きた}） | 300m |\r\n| 観覧車（{西|にし}） | 200m |\r\n| フードコート（{東|ひがし}） | 400m |\r\n| お化け屋敷（{南|みなみ}） | 500m |\r\n\r\nたとえば観覧車からフードコートに行くには、\r\n事務所を通って 200m＋400m＝**600m** 歩く{必要|ひつよう}があるよ。\r\n\r\n---\r\n\r\n### {事件|じけん}：ゴールドスターが消えた！\r\n\r\n今日の午後2時20分（14:20）ごろ、ワンダー園長が事務所に{戻|もど}ったら——\r\n**ゴールドスター・トロフィーが{棚|たな}から消えていた！**\r\n\r\n園長が最後に{確認|かくにん}したのは午後1時50分（13:50）。\r\n事務所の{窓|まど}は全部しまっていた。つまり**{出入口|でいりぐち}から入った人の犯行**。\r\n\r\nトロフィーが消えたのは **13:50〜14:20** の{間|あいだ}。\r\n\r\n---\r\n\r\n### {容疑者|ようぎしゃ}（あやしい人たち）\r\n\r\n事件の時間に遊園地で{働|はたら}いていた4人のスタッフ。\r\n{全員|ぜんいん}が「自分はその時間、事務所にいなかった」と言っている。\r\n\r\n| 名前 | 仕事 | 持ち場 | 歩はやく速さ |\r\n|---|---|---|---|\r\n| **ハヤアシ** | パークガイド | ジェットコースター（300m） | **100m/{分|ぷん}** |\r\n| **ノンビリおばちゃん** | チケット売り場 | 観覧車（200m） | **50m/分** |\r\n| **カケダシ** | アルバイト | お化け屋敷（500m） | **100m/分** |\r\n| **マモル** | {警備員|けいびいん} | フードコート（400m） | **100m/分** |\r\n\r\n**★ 歩く速さをメモしておこう！ あとで計算に使うよ！ ★**\r\n\r\n---\r\n\r\n### ルール\r\n\r\n1. **きみたちは{探偵|たんてい}だ。** {証拠|しょうこ}カードの情報と**計算**で犯人を見つけよう\r\n2. **えんぴつとメモ用紙を使おう。** このゲームは**算数の計算**がカギだよ\r\n3. **自分のキャラクターシートをよく読もう。** {秘密|ひみつ}の情報が書いてあるよ\r\n4. **他の人に見せていい情報と、秘密の情報がある。** 秘密は自分で「言うかどうか」を決めてね\r\n5. **正解・不正解はない。** 推理が当たっても外れても楽しめるよ。大事なのは「どう計算したか」\r\n6. **分からなくなったらGM（{進行役|しんこうやく}）にヒントをもらおう**\r\n\r\n---\r\n\r\n### ゲームの{流|なが}れ（3ステップ）\r\n\r\n| ステップ | やること | 時間 |\r\n|---|---|---|\r\n| ステップ1「{調査|ちょうさ}」 | 証拠カードを読んで、**計算してメモする。** 他の人に質問してもOK | 10分 |\r\n| ステップ2「{計算会議|けいさんかいぎ}」 | みんなで計算結果を持ち寄り、犯人は誰か考える | 10分 |\r\n| ステップ3「{推理発表|すいりはっぴょう}」 | 紙に犯人の名前と**計算の{根拠|こんきょ}**を書いて出す | 10分 |\r\n\r\n---\r\n\r\n### 使う算数の{公式|こうしき}\r\n\r\nこのゲームで使う公式はこの3つだけ！\r\n\r\n```\r\n★ {距離|きょり} ＝ 速さ × {時間|じかん}\r\n\r\n★ 時間 ＝ 距離 ÷ 速さ\r\n\r\n★ 速さ ＝ 距離 ÷ 時間\r\n```\r\n\r\nたとえば:\r\n- 100m/分の速さで300m歩くと → 300÷100＝**3分**かかる\r\n- 50m/分の速さで200m歩くと → 200÷50＝**4分**かかる\r\n\r\n**この計算ができれば、犯人が分かるよ！**\r\n",
  "evidenceCards": [
    {
      "number": 1,
      "title": "遊園地の地図（計算に使う！）",
      "content": "```\r\n                [ジェットコースター]\r\n                  ハヤアシの持ち場\r\n                       |\r\n                     300m\r\n                       |\r\n[{観覧車|かんらんしゃ}]--200m--[★{事務所|じむしょ}]--400m--[フードコート]\r\n ノンビリの持ち場              ↑事件{現場|げんば}        マモルの持ち場\r\n                       |\r\n                     500m\r\n                       |\r\n                [お化け{屋敷|やしき}]\r\n                  カケダシの持ち場\r\n```\r\n\r\n**★ 道は十字の形。どこに行くにも事務所を通る ★**\r\n\r\n**まとめ:**\r\n| 人物 | 持ち場 | 事務所からの{距離|きょり} |\r\n|---|---|---|\r\n| ハヤアシ | ジェットコースター | **300m** |\r\n| ノンビリ | 観覧車 | **200m** |\r\n| カケダシ | お化け屋敷 | **500m** |\r\n| マモル | フードコート | **400m** |\r\n\r\n---"
    },
    {
      "number": 2,
      "title": "みんなの歩く速さデータ",
      "content": "ワクワク遊園地では、スタッフ全員の歩く速さを{測|はか}っている。\r\n（園内は走ってはいけないルール！）\r\n\r\n| 名前 | 歩く速さ | メモ |\r\n|---|---|---|\r\n| ハヤアシ | **100m/{分|ぷん}** | パークガイド。歩き慣れている |\r\n| ノンビリおばちゃん | **50m/分** | ゆっくり歩き。他の人の{半分|はんぶん}の速さ |\r\n| カケダシ | **100m/分** | 元気で足が速い。走れば200m/分だが、園内は{走行|そうこう}{禁止|きんし} |\r\n| マモル | **100m/分** | 毎日計測。{正確|せいかく}な{数値|すうち} |\r\n\r\n**★ この速さと距離を使って計算するよ！ ★**\r\n\r\n**計算の{公式|こうしき}:**\r\n```\r\n{時間|じかん}（分） ＝ {距離|きょり}（m） ÷ 速さ（m/分）\r\n```\r\n\r\n**れんしゅう:**\r\nハヤアシが事務所からジェットコースターまで歩くと →\r\n300m ÷ 100m/分 ＝ **3分**\r\n\r\nノンビリおばちゃんが事務所から観覧車まで歩くと →\r\n200m ÷ 50m/分 ＝ **4分**\r\n\r\n---"
    },
    {
      "number": 3,
      "title": "{目撃|もくげき}情報（アリバイの{証言|しょうげん}）",
      "content": "お客さんやスタッフの目撃証言をまとめた。\r\nそれぞれのスタッフが「いた」のを{確認|かくにん}できた{時刻|じこく}と、\r\n**「いなかった時間」**を{記録|きろく}した。\r\n\r\n### ハヤアシ（ジェットコースター{担当|たんとう}）\r\n- 14:00 ジェットコースター前にいた ← お客さんが確認\r\n- 14:05〜14:10 **{姿|すがた}が見えなかった**（5{分間|ふんかん}）\r\n- 14:10 ジェットコースター前に戻っていた ← お客さんが確認\r\n\r\n→ **{空白|くうはく}時間: 5分**\r\n\r\n### ノンビリおばちゃん（観覧車チケット売り場）\r\n- 14:00 チケット売り場にいた ← お客さんが確認\r\n- 14:02〜14:08 **姿が見えなかった**（6分間）\r\n- 14:08 チケット売り場に戻っていた ← お客さんが確認\r\n\r\n→ **空白時間: 6分**\r\n\r\n### カケダシ（お化け屋敷担当）\r\n- 13:50 お化け屋敷の中にいた ← お客さんが確認\r\n- 13:55〜14:15 **姿が見えなかった**（20分間）\r\n- 14:15 お化け屋敷の中にいた ← お客さんが確認\r\n\r\n→ **空白時間: 20分**\r\n\r\n### マモル（フードコート{巡回|じゅんかい}）\r\n- 14:08 フードコートにいた ← お客さんが確認\r\n- 14:10〜14:17 **姿が見えなかった**（7分間）\r\n- 14:17 フードコートに戻っていた ← お客さんが確認\r\n\r\n→ **空白時間: 7分**\r\n\r\n**★ 全員に「いなかった時間」がある！ 全員あやしい！ ★**\r\n\r\n---"
    },
    {
      "number": 4,
      "title": "アリバイを計算で{検証|けんしょう}する方法",
      "content": "犯人は「空白時間」の{間|あいだ}に、持ち場→事務所→持ち場を**{往復|おうふく}**したはず。\r\n本当にそれが{可能|かのう}だったか、計算で確かめよう！\r\n\r\n### やり方\r\n\r\n```\r\nステップ① {往復|おうふく}の{距離|きょり}を出す\r\n    事務所までの距離 × 2 ＝ 往復の距離\r\n\r\nステップ② 往復にかかる時間を出す\r\n    往復の距離 ÷ 歩く速さ ＝ かかる時間\r\n\r\nステップ③ くらべる\r\n    かかる時間 ＞ 空白時間 → 間に合わない！（シロ✓）\r\n    かかる時間 ＜ 空白時間 → 間に合う！！（クロ★）\r\n```\r\n\r\n**{例題|れいだい}：** もし往復に**10分**かかるのに、空白時間が**5分**しかなかったら？\r\n→ 10分 ＞ 5分 → 間に合わない！ =シロ✓（往復するのにぜんぜん時間が{足|た}りないね）\r\n\r\n### {計算表|けいさんひょう}（ここに書き込もう！）\r\n\r\n| 名前 | 距離 | ×2 ＝ 往復 | ÷速さ ＝ かかる時間 | 空白時間 | {判定|はんてい} |\r\n|---|---|---|---|---|---|\r\n| ハヤアシ | 300m | 　 m | 　 ÷ 100 ＝ 　 分 | 5分 | |\r\n| ノンビリ | 200m | 　 m | 　 ÷ 50 ＝ 　 分 | 6分 | |\r\n| カケダシ | 500m | 　 m | 　 ÷ 100 ＝ 　 分 | 20分 | |\r\n| マモル | 400m | 　 m | 　 ÷ 100 ＝ 　 分 | 7分 | |\r\n\r\n**★ 全員分を計算して、表をうめてみよう！ ★**\r\n\r\n---"
    }
  ],
  "evidence5": {
    "number": 5,
    "title": "（★ステップ2の{途中|とちゅう}でGMが配る★）",
    "content": "### 2つの新しい手がかり\r\n\r\n#### 手がかりA：{歩数計|ほすうけい}のデータ\r\n\r\n遊園地のスタッフは全員、{歩数計|ほすうけい}（歩いた歩数をカウントする{機械|きかい}）をつけている。\r\n13:55〜14:15のデータを{確認|かくにん}したところ——\r\n\r\n| 名前 | 13:55〜14:15の歩数 | 1歩の長さ | 歩いた距離（計算してみよう） |\r\n|---|---|---|---|\r\n| ハヤアシ | 400歩 | 0.7m | 400×0.7＝**280m** |\r\n| ノンビリ | 320歩 | 0.5m | 320×0.5＝**160m** |\r\n| カケダシ | 1600歩 | 0.7m | 1600×0.7＝**1120m** |\r\n| マモル | 500歩 | 0.8m | 500×0.8＝**400m** |\r\n\r\n**考えてみよう：**\r\n- カケダシは20分間で**1120m**も歩いている！\r\n- お化け屋敷に「ずっといた」なら、そんなに歩くはずがない\r\n- お化け屋敷↔事務所の往復は500m×2＝**1000m**。1120mとほぼ{一致|いっち}！\r\n- 残りの120mは事務所の中を歩き回った分？\r\n\r\n#### 手がかりB：お化け屋敷の{秘密|ひみつ}の{倉庫|そうこ}\r\n\r\n探偵団がお化け屋敷を{調|しら}べたところ——\r\nステージ{裏|うら}の**秘密の倉庫**に、タオルに{包|つつ}まれた**ゴールドスター・トロフィー**が{隠|かく}されていた！\r\n\r\nこの倉庫の場所を知っているのは、お化け屋敷担当の**カケダシだけ**。\r\n\r\n**考えてみよう：**\r\n- 計算結果とこの証拠を合わせると、犯人は……？"
  },
  "characters": [
    {
      "id": "hayaashi",
      "name": "ハヤアシ",
      "role": "100m/分",
      "isNPC": false,
      "introContent": "",
      "publicContent": "- 「私は14:00ごろ、ジェットコースターのそばにいました」\r\n- 「お客さんの案内で忙しかったです。ずっとジェットコースターのあたりにいたはず」\r\n- 「歩く速さは100m/分です。パークガイドですから、園内は歩き慣れています」\r\n- 「事務所には用事がなかったので、行っていません」\r\n\r\n---",
      "fullContent": "# キャラクターシート：ハヤアシ\r\n\r\n## ★ きみはこの人になりきってね ★\r\n\r\n---\r\n\r\n### きみはだれ？\r\n\r\n**ハヤアシ**——ワクワク遊園地のパークガイド。25歳さい。\r\nテキパキ仕事をする元気な{女性|じょせい}。\r\nお客さんを{案内|あんない}したり、{迷子|まいご}の{対応|たいおう}をしたり大忙おおいそがし。\r\n\r\n歩くのが速い。いつもサクサク園内を歩き回っている。\r\n**歩く速さ: 100m/{分|ぷん}**\r\n\r\n持ち場: ジェットコースター（{事務所|じむしょ}から**300m**{北|きた}）\r\n\r\n---\r\n\r\n### みんなに言っていい情報（{公開|こうかい}情報）\r\n\r\n- 「私は14:00ごろ、ジェットコースターのそばにいました」\r\n- 「お客さんの案内で忙しかったです。ずっとジェットコースターのあたりにいたはず」\r\n- 「歩く速さは100m/分です。パークガイドですから、園内は歩き慣れています」\r\n- 「事務所には用事がなかったので、行っていません」\r\n\r\n---\r\n\r\n### ★{秘密|ひみつ}の情報★（他の人に見せちゃダメ！）\r\n\r\nきみは犯人ではない。でも{隠|かく}していることがある。\r\n\r\n**本当のこと:**\r\n14:05〜14:10の5分間、ジェットコースターの{裏|うら}でスマホを見ていた。\r\nちょっとサボってSNSをチェックしていたんだ。\r\n\r\nその5分間だけ、誰にも{目撃|もくげき}されていない。\r\n「サボっていた」がバレると園長に怒られるので{言|い}たくない。\r\n\r\n**でも犯人じゃない！ 計算すれば分かるはず……**\r\n\r\n---\r\n\r\n### きみの{目標|もくひょう}\r\n\r\n- 犯人じゃないことを証明したい\r\n- でも「サボっていた5分間」は{言|い}たくない\r\n- 追いつめられたら、正直に「5分間スマホを見ていた」と告白する\r\n\r\n---\r\n\r\n### ヒント（行きづまったら読んでね）\r\n\r\n- きみの空白時間は5分。ジェットコースターは事務所から300m\r\n- 事務所に行って戻るには: 300m×2＝600m。600÷100＝**6分**かかる\r\n- 5分しか空白がないから、6分の{往復|おうふく}は{物理的|ぶつりてき}にムリ！\r\n- この計算を他の人に教えてあげてもいいよ。「計算したら私じゃないって分かるよ」って\r\n",
      "imageUrl": "/images/math-01/char-hayaashi.webp"
    },
    {
      "id": "kakedashi",
      "name": "カケダシ",
      "role": "100m/分",
      "isNPC": false,
      "introContent": "",
      "publicContent": "- 「おれはお化け屋敷の{担当|たんとう}です。お化けの{準備|じゅんび}とか、お客さんの{案内|あんない}とか」\r\n- 「14:00ごろはお化け屋敷にいたはず。ずっと中にいましたよ」\r\n- 「歩く速さは100m/分です。走ればもっと速いけど、園内は走っちゃダメなので」\r\n- 「ゴールドスター……あれ、じいちゃんが作ったやつですよね。大事なトロフィーだ」\r\n\r\n---",
      "fullContent": "# キャラクターシート：カケダシ\r\n\r\n## ★ きみはこの人になりきってね ★\r\n\r\n---\r\n\r\n### きみはだれ？\r\n\r\n**カケダシ**——遊園地のアルバイト。15歳さい。\r\n中学3年生。{放課後|ほうかご}と休日に遊園地で{働|はたら}いている。\r\n元気で足が速く、何でも{全力|ぜんりょく}でやるタイプ。\r\n\r\n子どものころ、ワンダーじいちゃん（前園長）にかわいがってもらっていた。\r\nじいちゃんが作ったゴールドスターの話を聞いて育った。\r\n\r\n**歩く速さ: 100m/{分|ぷん}**\r\n\r\n持ち場: お化け{屋敷|やしき}（事務所から**500m**{南|みなみ}）\r\n\r\n---\r\n\r\n### みんなに言っていい情報（{公開|こうかい}情報）\r\n\r\n- 「おれはお化け屋敷の{担当|たんとう}です。お化けの{準備|じゅんび}とか、お客さんの{案内|あんない}とか」\r\n- 「14:00ごろはお化け屋敷にいたはず。ずっと中にいましたよ」\r\n- 「歩く速さは100m/分です。走ればもっと速いけど、園内は走っちゃダメなので」\r\n- 「ゴールドスター……あれ、じいちゃんが作ったやつですよね。大事なトロフィーだ」\r\n\r\n---\r\n\r\n### ★{秘密|ひみつ}の情報★（他の人に見せちゃダメ！）\r\n\r\n**きみが{犯人|はんにん}だ。**\r\n\r\nゴールドスターを事務所から持ち出したのは、きみだ。\r\n\r\n**なぜやったのか？**\r\n先週、ワンダー園長がこう言っていた。\r\n\r\n> 「ゴールドスターも古くなったし、来月新しいトロフィーに{交換|こうかん}するよ。\r\n> 　古い方は{処分|しょぶん}かな」\r\n\r\n**処分——？ あの、じいちゃんが手作りしたゴールドスターを{捨|す}てる？**\r\n\r\nワンダーじいちゃんは、おれが子どものとき毎日遊園地に遊びに来ていたおれに\r\n「このゴールドスターはな、遊園地を楽しんでくれる人みんなの星なんだ」と言ってくれた。\r\n\r\nそんな大切なものを捨てるなんて、{絶対|ぜったい}にダメだ。\r\n\r\nだからおれは昨日のうちに計画を立てた。\r\n今日の13:55にお化け屋敷を出て、100m/分で事務所に向かった。\r\n5分で事務所に{着|き}、トロフィーをタオルで{包|つつ}んで持ち出した。\r\nそして事務所を14:10に出発、5分歩いて14:15にお化け屋敷に戻った。\r\nトロフィーはお化け屋敷の**{秘密|ひみつ}の{倉庫|そうこ}**に{隠|かく}した。\r\n\r\n**犯行タイムライン:**\r\n- 13:55 お化け屋敷を出る\r\n- 14:00 事務所に到着（500m÷100m/分＝5分）\r\n- 14:00〜14:10 トロフィーを包んで持ち出す\r\n- 14:10 事務所を出発\r\n- 14:15 お化け屋敷に帰還（500m÷100m/分＝5分）\r\n\r\n---\r\n\r\n### きみの{目標|もくひょう}\r\n\r\n- できるだけバレないようにする\r\n- 「お化け屋敷にずっといた」と主張し続ける\r\n- 計算で「往復できる」と{指摘|してき}されたら →「お化け屋敷の中は広いから、中を歩き回っていただけだよ。外には出てない」と{反論|はんろん}する\r\n- それでも追いつめられたら——じいちゃんのトロフィーへの思いを正直に話す\r\n- 「捨てるなんて許せなかった。おれはトロフィーを守ったんだ」と堂々と言う\r\n\r\n---\r\n\r\n### ヒント（行きづまったら読んでね）\r\n\r\n- きみの{弱点|じゃくてん}①: 空白時間が20分もある。他の人は5〜7分なのに、きみだけ長すぎる\r\n- きみの弱点②: 500m×2＝1000m。1000÷100＝10分。20分の空白で往復10分は{楽|らく}にできてしまう\r\n- きみの弱点③: お化け屋敷は事務所から一番遠い（500m）のに、空白時間が一番長い。ここに{矛盾|むじゅん}がある\r\n- 追いつめられたら、じいちゃんの話をしよう。{動機|どうき}を話せば、みんなは理解してくれるはず\r\n",
      "imageUrl": "/images/math-01/char-kakedashi.webp"
    },
    {
      "id": "mamoru",
      "name": "マモル",
      "role": "100m/分",
      "isNPC": false,
      "introContent": "",
      "publicContent": "- 「私は14:00ごろ、フードコートで巡回中でした」\r\n- 「警備員ですから、時間には正確です。自分の行動を正確に覚えています」\r\n- 「歩く速さは100m/分です。毎日{計測|けいそく}していますので間違いありません」\r\n- 「ゴールドスターが盗まれたと聞いて、私も犯人を{捕|つか}まえたいです」\r\n\r\n---",
      "fullContent": "# キャラクターシート：マモル\r\n\r\n## ★ きみはこの人になりきってね ★\r\n\r\n---\r\n\r\n### きみはだれ？\r\n\r\n**マモル**——遊園地の{警備員|けいびいん}。22歳さい。\r\nまじめで{几帳面|きちょうめん}な{性格|せいかく}。\r\n「お客さんの{安全|あんぜん}を守る」が仕事のモットー。\r\n\r\nいつも園内を{巡回|じゅんかい}していて、時間にも{正確|せいかく}。\r\n自分の歩く速さまで正確に知っている。\r\n**歩く速さ: 100m/{分|ぷん}**\r\n\r\n持ち場: フードコート（事務所から**400m**{東|ひがし}）\r\n\r\n---\r\n\r\n### みんなに言っていい情報（{公開|こうかい}情報）\r\n\r\n- 「私は14:00ごろ、フードコートで巡回中でした」\r\n- 「警備員ですから、時間には正確です。自分の行動を正確に覚えています」\r\n- 「歩く速さは100m/分です。毎日{計測|けいそく}していますので間違いありません」\r\n- 「ゴールドスターが盗まれたと聞いて、私も犯人を{捕|つか}まえたいです」\r\n\r\n---\r\n\r\n### ★{秘密|ひみつ}の情報★（他の人に見せちゃダメ！）\r\n\r\nきみは犯人ではない。でも{恥|はず}かしい秘密がある。\r\n\r\n**本当のこと:**\r\n14:10〜14:17の7分間、フードコートを{離|はなれ}ていた。\r\n理由：急にお腹なかが{痛|いた}くなって、フードコートの近くのトイレに走った。\r\n\r\n警備員が「お腹痛いのでトイレ行きました」なんてカッコ悪い。\r\nだから「ずっとフードコートにいた」と{言|い}たい。\r\n\r\n**でも犯人じゃない！ 計算すれば分かるはず！**\r\n\r\n---\r\n\r\n### きみの{目標|もくひょう}\r\n\r\n- 犯人じゃないことを証明したい\r\n- でも「トイレに行っていた」はなるべく{言|い}たくない\r\n- 追いつめられたら、まじめに告白。「実は……急にお腹が……」\r\n\r\n---\r\n\r\n### ヒント（行きづまったら読んでね）\r\n\r\n- きみの空白時間は7分。フードコートは事務所から400m\r\n- 事務所に行って戻るには: 400m×2＝800m。800÷100＝**8分**かかる\r\n- 7分しか空白がないから、8分の{往復|おうふく}は間に合わない！\r\n- 警備員らしく堂々と計算結果を{示|しめ}そう。「数字は嘘をつきません」\r\n",
      "imageUrl": "/images/math-01/char-mamoru.webp"
    },
    {
      "id": "nonbiri",
      "name": "ノンビリおばちゃん",
      "role": "50m/分",
      "isNPC": false,
      "introContent": "",
      "publicContent": "- 「あたしは観覧車のそばのチケット売り場にいたよ〜」\r\n- 「ずっと{座|すわ}ってチケットを売っていたさ。立つのも{面倒|めんどう}でねぇ」\r\n- 「歩くのは{遅|おそ}いよ〜。50m/分くらいかねぇ。急いでもこんなもんさ」\r\n- 「トロフィー？ あたしが持って歩いたら重くて進めないよ〜」\r\n\r\n---",
      "fullContent": "# キャラクターシート：ノンビリおばちゃん\r\n\r\n## ★ きみはこの人になりきってね ★\r\n\r\n---\r\n\r\n### きみはだれ？\r\n\r\n**ノンビリおばちゃん**——チケット売り場のベテランスタッフ。58歳さい。\r\n遊園地が開園した30年前から{働|はたら}いている。\r\nワンダーじいちゃん（前えんちょう）のことも知っている。\r\n\r\nのんびりした{性格|せいかく}で、歩くのもゆっくり。\r\n**歩く速さ: 50m/{分|ぷん}**（他の人の{半分|はんぶん}！）\r\n\r\n持ち場: {観覧車|かんらんしゃ}のそば（事務所から**200m**{西|にし}）\r\n\r\n---\r\n\r\n### みんなに言っていい情報（{公開|こうかい}情報）\r\n\r\n- 「あたしは観覧車のそばのチケット売り場にいたよ〜」\r\n- 「ずっと{座|すわ}ってチケットを売っていたさ。立つのも{面倒|めんどう}でねぇ」\r\n- 「歩くのは{遅|おそ}いよ〜。50m/分くらいかねぇ。急いでもこんなもんさ」\r\n- 「トロフィー？ あたしが持って歩いたら重くて進めないよ〜」\r\n\r\n---\r\n\r\n### ★{秘密|ひみつ}の情報★（他の人に見せちゃダメ！）\r\n\r\nきみは犯人ではない。でもちょっと{恥|はず}かしい秘密がある。\r\n\r\n**本当のこと:**\r\n14:02〜14:08の6分間、チケット売り場を{離|はなれ}ていた。\r\n理由：売り場の{裏|うら}にある{自動販売機|じどうはんばいき}でジュースを買って飲んでいた。\r\n\r\n「{勤務中|きんむちゅう}におやつ」がバレると園長に注意される。\r\nだからチケット売り場に「ずっといた」と{言|い}たい。\r\n\r\n**でも犯人じゃない！ あたしの足じゃ間に合わないはず……**\r\n\r\n---\r\n\r\n### きみの{目標|もくひょう}\r\n\r\n- 犯人じゃないことを証明したい\r\n- でも「おやつタイム」がバレるのは恥ずかしい\r\n- 追いつめられたら、のんびりと告白。「いや〜ちょっとジュース飲んでてねぇ」\r\n\r\n---\r\n\r\n### ヒント（行きづまったら読んでね）\r\n\r\n- きみの空白時間は6分。観覧車は事務所から200m\r\n- 事務所に行って戻るには: 200m×2＝400m。400÷50＝**8分**かかる\r\n- 6分しか空白がないから、8分の{往復|おうふく}は足が遅いきみにはムリ！\r\n- ノンビリおばちゃんらしく、のんびり構えていればOK。「あたしの足で事務所まで往復？ ムリムリ〜」\r\n",
      "imageUrl": "/images/math-01/char-nonbiri.webp"
    },
    {
      "id": "npc-4",
      "name": "{ワンダー園長",
      "role": "—",
      "isNPC": true,
      "introContent": "",
      "publicContent": "",
      "fullContent": ""
    }
  ],
  "solution": "# {解決編|かいけつへん}\r\n\r\n## 〜 ステップ3の{投票|とうひょう}が終わったら、GMが読み上げてね 〜\r\n\r\n---\r\n\r\n### {真相|しんそう}発表！\r\n\r\nみんな、計算おつかれさま！\r\nそれでは、ゴールドスター・トロフィーを持ち出した犯人を発表するよ。\r\n\r\n---\r\n\r\n### {犯人|はんにん}は——\r\n\r\n## **カケダシ**\r\n\r\nお化け屋敷{担当|たんとう}のアルバイト少年、カケダシ。\r\nこの子がゴールドスターを事務所から持ち出した。\r\n\r\n---\r\n\r\n### 計算で{証明|しょうめい}！ アリバイ{検証|けんしょう}の答え合わせ\r\n\r\n| 名前 | {距離|きょり} | {往復|おうふく} | ÷速さ | かかる時間 | {空白|くうはく}時間 | {判定|はんてい} |\r\n|---|---|---|---|---|---|---|\r\n| ハヤアシ | 300m | 600m | ÷100 | **6分** | 5分 | 6＞5 **ムリ✓** |\r\n| ノンビリ | 200m | 400m | ÷50 | **8分** | 6分 | 8＞6 **ムリ✓** |\r\n| カケダシ | 500m | 1000m | ÷100 | **10分** | 20分 | 10＜20 **デキル★** |\r\n| マモル | 400m | 800m | ÷100 | **8分** | 7分 | 8＞7 **ムリ✓** |\r\n\r\n**カケダシだけが、往復にかかる時間（10分）よりも長い空白時間（20分）を持っていた！**\r\n残りの10分でトロフィーを持ち出す時間も{十分|じゅうぶん}にあった。\r\n\r\nさらに{歩数計|ほすうけい}のデータ:\r\n- カケダシの{歩行|ほこう}{距離|きょり}: 1600歩×0.7m＝**1120m**\r\n- お化け屋敷↔事務所の往復: 500m×2＝**1000m**\r\n- ほぼ{一致|いっち}！（差の120mは事務所内を歩いた分）\r\n\r\n---\r\n\r\n### カケダシはなぜトロフィーを持ち出した？\r\n\r\nカケダシはトロフィーを「{盗|ぬす}んだ」のではなかった。**「守った」**のだ。\r\n\r\n先週、ワンダー園長がこう言っていた。\r\n「ゴールドスターも古くなったから、来月新しいものに{交換|こうかん}しよう」\r\n\r\nゴールドスターは、園長のお父さん——ワンダーじいちゃんが30年前に手作りした宝物。\r\nカケダシは子どものころ、じいちゃんからこう聞いていた。\r\n\r\n> 「このゴールドスターはな、遊園地を楽しんでくれる人みんなの星なんだ。\r\n> 　おじいちゃんの心が{詰|つ}まっているんだよ」\r\n\r\nそんな大切な物を{処分|しょぶん}するなんて、カケダシには{許|ゆる}せなかった。\r\nだからお化け屋敷の{秘密|ひみつ}の倉庫に隠した。\r\n園長に気づいてもらえるまで、ずっと守り続けるつもりだった。\r\n\r\n---\r\n\r\n### 各キャラクターの{秘密|ひみつ}\r\n\r\n| キャラクター | 秘密 | 空白時間の本当の理由 |\r\n|---|---|---|\r\n| **ハヤアシ** | 5分間スマホでSNSを見てサボっていた | サボりがバレたくなかった |\r\n| **ノンビリおばちゃん** | 6分間ジュースを買いに行っていた | {勤務中|きんむちゅう}のおやつがバレたくなかった |\r\n| **カケダシ** | **犯人。** 20分で事務所を往復し、トロフィーを隠した | じいちゃんの思い出を守りたかった |\r\n| **マモル** | 7分間トイレに行っていた | 警備員としてカッコ悪いから言えなかった |\r\n\r\n---\r\n\r\n### みんなのアリバイを図にすると\r\n\r\n```\r\n13:50    13:55    14:00    14:05    14:10    14:15    14:17    14:20\r\n  |        |        |        |        |        |        |        |\r\n  |        |        |  ハヤアシ ████空白████ いた     |        |\r\n  |        |        |  いた   |見えない|        |        |        |\r\n  |        |        |        |        |        |        |        |\r\n  |        |  ノンビリ ██空白██████ いた    |        |        |\r\n  |        |  いた   |見えない    |        |        |        |\r\n  |        |        |        |        |        |        |        |\r\n  |  カケダシ████████████空白████████████████ いた    |        |\r\n  |  いた   |見えない（20分間！）            |        |        |\r\n  |        |        |        |        |        |        |        |\r\n  |        |        |  マモル |  いた  ███空白███████ いた   |\r\n  |        |        |        |        |見えない        |        |\r\n  |        |        |        |        |        |        |        |\r\n  |        |  ←───── 犯行可能時間 13:50〜14:20 ─────→  |\r\n```\r\n\r\nカケダシの空白（20分）だけが犯行時間をすっぽりカバーしている！\r\n\r\n---\r\n\r\n### {学習|がくしゅう}ポイントのふりかえり\r\n\r\n#### ① 速さ×時間＝距離の使い方\r\n\r\n今回きみたちがやった計算:\r\n\r\n```\r\n往復の距離 ＝ {片道|かたみち}の距離 × 2\r\nかかる時間 ＝ 往復の距離 ÷ 歩く速さ\r\n```\r\n\r\nこの計算で「物理的に可能かどうか」を証明した。\r\nこれは算数であり、同時に**{論理的思考|ろんりてきしこう}**でもある。\r\n\r\n**算数は問題を解くだけのものじゃない。**\r\n**事実を証明するための「{武器|ぶき}」なんだ。**\r\n\r\n#### ② 速さが違うと何が変わる？\r\n\r\nノンビリおばちゃん（50m/分）とハヤアシ（100m/分）を{比|くら}べてみよう:\r\n\r\n- 同じ200mの道のり:\r\n  - ノンビリ: 200÷50＝**4分**\r\n  - ハヤアシ: 200÷100＝**2分**\r\n- 速さが半分だと、かかる時間は**2倍**になる！\r\n\r\nだからノンビリおばちゃんは、距離が近い（200m）のにかかる時間が長い（8分）。\r\n**速さを無視して距離だけ見ると、{間違|まちが}った{推理|すいり}をしてしまう。**\r\n\r\n#### ③ 「アリバイ」って何？\r\n\r\nアリバイ（alibi）はラテン語で「{別|べつ}の{場所|ばしょ}に」という{意味|いみ}。\r\n「事件のとき自分は別の場所にいたから犯人じゃない」という証明のこと。\r\n\r\nでも今回のように、**計算で「本当にそこにいられたのか」を検証できる。**\r\nテレビの{刑事|けいじ}ドラマでも、距離と時間の計算でアリバイを崩す場面があるよ。\r\n\r\n#### ④ 歩数計のデータも算数！\r\n\r\n証拠カード5の歩数計データ:\r\n```\r\n歩いた距離 ＝ 歩数 × 1歩の長さ\r\n```\r\nこれも「かけ算」だ。カケダシの 1600歩×0.7m＝**1120m** が決定的だったね。\r\n\r\n---\r\n\r\n### チャレンジ問題（やってみよう！）\r\n\r\n#### 問題1\r\nもしカケダシの歩く速さが 80m/分 だったら、往復にかかる時間は何分？\r\n犯行はまだ可能？\r\n\r\n> ヒント: 1000m÷80m/分＝？分\r\n\r\n#### 問題2\r\nもしお化け屋敷が事務所から **1200m** の場所にあったら、\r\nカケダシは20分で往復できる？\r\n\r\n> ヒント: 1200×2÷100＝？分\r\n\r\n#### 問題3\r\nノンビリおばちゃんの空白時間が**10分**だったら、\r\nおばちゃんは事務所を往復できた？\r\n\r\n> ヒント: 400m÷50m/分＝？分\r\n\r\n---\r\n\r\n### チャレンジ問題の答え\r\n\r\n**問題1:** 1000÷80＝**12.5分**。空白20分＞12.5分なので、まだ犯行可能！\r\n**問題2:** 1200×2＝2400m。2400÷100＝**24分**。空白20分＜24分なので往復できない！\r\n**問題3:** 400÷50＝**8分**。空白10分＞8分なので往復できる！（おばちゃんも容疑者に！）\r\n\r\n**数字が1つ変わるだけで、犯人が変わることもある。だから計算は{正確|せいかく}に！**\r\n",
  "gmGuide": "# GM（{進行役|しんこうやく}）ガイド\n\n## ナゾトキ探偵団 数字の迷宮 Vol.1「消えたゴールドスターと4つのアリバイ」\n\n---\n\n### このガイドの使い方\n\nGMが初めての方でも大丈夫！\nこのガイドに沿って進めれば、30〜45分で楽しくプレイできます。\n\n**このシナリオの特別ポイント:**\n通常のマダミスと違い、**算数の計算が推理の核**です。\nプレイヤーには必ず**えんぴつとメモ用紙**を渡してください。\n計算が得意な子がリードし、苦手な子を助ける——という協力も生まれます。\n\n**GMの役割:**\n- ワンダー園長（NPC）を演じる\n- 証拠カードを配るタイミングを管理する\n- **計算に詰まった子をサポートする**（答えは教えず、やり方をヒント）\n\n---\n\n### {事前準備|じぜんじゅんび}（10分）\n\n**このサイトでの準備:**\n- プレイヤーページを参加者に共有（URLまたはQRコード）\n- 印刷して配布する場合は、このページ下部の「GMツール」から「カード一式を印刷」へ\n- ペンとメモ用紙（各プレイヤー分）\n- タイマー（スマホ可）\n- 投票用の紙（人数分）\n\n2. **準備物:**\n   - **えんぴつとメモ用紙**（各プレイヤー分。★必須！）\n   - タイマー（スマホ可）\n   - 投票用の紙\n\n3. **キャラクター割り当て:**\n\n| プレイ人数 | 割り当て | NPCにするキャラ |\n|---|---|---|\n| 2人（親子） | 子ども→カケダシ or マモル、親→ハヤアシ（+GM） | ノンビリ |\n| 3人 | ハヤアシ、カケダシ、マモル | ノンビリ |\n| 3人（別パターン） | ノンビリ、カケダシ、マモル | ハヤアシ |\n| 4人 | ハヤアシ、ノンビリ、カケダシ、マモル | なし |\n\n**NPCの扱い:**\nNPCキャラの公開情報はGMが代わりに伝えます。\nノンビリがNPCの場合: 「あたしはずっと観覧車にいたよ〜。50m/分でしか歩けないし」\nハヤアシがNPCの場合: 「ジェットコースターにいました。100m/分で歩きます」\n\n---\n\n### ゲーム{進行|しんこう}\n\n#### 開始前：{導入|どうにゅう}（3分）\n\nGMが読み上げる:\n\n> 「みなさん、今日は『ナゾトキ探偵団——数字の迷宮』の時間です。\n> 　ワクワク遊園地でトロフィーが消えた事件を解決してもらいます。\n>\n> 　★今回のゲームは、算数の計算で犯人を見つけます！\n> 　★えんぴつとメモ用紙を準備してね。計算が武器だよ！\n>\n> 　まずは共通情報を読んでください。\n> 　★特に『遊園地の地図』と『速さの公式』はとても大事。メモしておこう」\n\n共通情報（共通情報）とキャラクターシートを配る。\n全員が読み終わるまで2〜3分待つ。\n\n**地図の距離と各人の速さをメモしたか確認してください。** ここが全ての基盤です。\n\n---\n\n#### ステップ1：{調査|ちょうさ}（10〜12分）\n\nGMが読み上げる:\n\n> 「ステップ1、調査タイムです！\n> 　証拠カードを配ります。特に**証拠カード4**に計算の表があります。\n> 　この表を{埋|う}めるのが最初のミッションだよ。\n> 　他のキャラクターに質問してもOK。制限時間は10分！」\n\n**証拠カード1〜4を配る。**\n\n**★ 計算{担当|たんとう}ルール（{重要|じゅうよう}！）:**\n> 「まずは**自分のキャラクター**の往復時間を自分で計算してね。\n> 　計算できたら、グループで結果を{共有|きょうゆう}しよう！」\n\n計算が{得意|とくい}な子が全部やってしまうと、他の子の学びが減ります。\n**各プレイヤーが自分のキャラの計算を担当**するようにしてください。\n全員が計算を終えてから、結果を{突|つ}き合わせて「誰が往復可能か」を{議論|ぎろん}する流れが{理想|りそう}です。\n\n**GMのやること:**\n- タイマーを10〜12分にセット（計算時間が必要なので少し長めにしてOK）\n- ワンダー園長として嘆く:\n  - 「じいちゃんの作ったトロフィーが……見つけてくれ〜！」\n  - 「犯人は必ずこの4人の中にいるはずだ！」\n- **計算に詰まっている子がいたら助ける**（下の「計算サポート」参照）\n\n---\n\n#### ステップ2：{計算会議|けいさんかいぎ}（10分）\n\nGMが読み上げる:\n\n> 「ステップ2、計算会議の時間です！\n> 　みんなの計算結果を持ち寄って、犯人は誰か考えよう。\n> 　『この人は計算上ムリ』『この人は計算上デキル』を整理してね」\n\n**5分経過したら、証拠カード5を配る。**\n\nGMが読み上げる:\n\n> 「新しい証拠が出てきたぞ！ 歩数計のデータだ。計算してみよう！」\n\n**証拠カード5の歩数計データは追加の「かけ算」。**\n歩数×1歩の長さ＝歩いた距離、という計算です。\n\n---\n\n#### ステップ3：{推理発表|すいりはっぴょう} + {投票|とうひょう}（10分）\n\nGMが読み上げる:\n\n> 「最後のステップです！\n> 　紙に『犯人の名前』と『計算の{根拠|こんきょ}』を書いてください。\n> 　数字で証明しよう！ 書けたらオープン！」\n\n**全員が書き終わったら:**\n1. 一斉にオープン\n2. 1人ずつ、自分の推理と**計算根拠**を発表\n3. 解決編（解決編）を読み上げる\n\n**大事なポイント:**\n- 答えが合っていたら「計算バッチリ！」とほめる\n- 答えが違っていたら「どこで計算が違ったか」一緒に確認する\n- **間違いも学び。** 「ここをこう計算すると正解に近づくよ」と建設的に\n\n---\n\n### 計算サポート（子どもが詰まったとき）\n\n#### よくある詰まりポイントと声かけ\n\n| 詰まりポイント | GMの声かけ |\n|---|---|\n| 何を計算すればいいか分からない | 「証拠カード4の表を見て。まず『距離×2』をやってみよう」 |\n| 往復の意味が分からない | 「行って帰ってくるんだよ。300m行って300m戻ると、全部で何m？」 |\n| ÷（割り算）で詰まる | 「600÷100は？ 100が何個で600になる？ 6個だね。だから6分！」 |\n| ノンビリの50m/分が難しい | 「400÷50。50が何個で400？ 50、100、150…… 8個で400。だから8分！」 |\n| 「全員ムリじゃん」と勘違い | 「もう一度カケダシの計算をやってみて。10分と20分、どっちが大きい？」 |\n| 歩数計の計算 | 「1600歩×0.7m。まず1600×7＝？ そこから小数点を戻そう」 |\n\n#### 計算が苦手な子へのフォロー\n\n- **紙に数直線を{書|か}せる**: 0m、100m、200m……と目盛りを書いて「ここからここまで何分？」\n- **具体的な場面で考えさせる**: 「100m走を1分で走る人がいるとしたら、300mだと？」\n- **電卓の使用**: 計算そのものより推理に集中させたい場合は、電卓OKにしてもいい\n\n---\n\n### タイムスケジュール（{目安|めやす}）\n\n| 時間 | 内容 |\n|---|---|\n| 0:00-0:03 | 導入＋共通情報・キャラクターシート配布 |\n| 0:03-0:15 | ステップ1：調査＋計算（証拠カード1〜4配布）|\n| 0:15-0:28 | ステップ2：計算会議（0:20ごろに証拠カード5追加）|\n| 0:28-0:38 | ステップ3：推理発表＋投票 |\n| 0:38-0:45 | 解決編＋チャレンジ問題 |\n\n**時間が余ったら:** 解決編のチャレンジ問題を出す（数字を変えて再計算）\n**時間が足りなければ:** ステップ1の計算を全員で一緒にやる（GMが板書）\n\n---\n\n### {親子|おやこ}プレイの場合\n\n#### 親の役割\n\n- **GM＋1キャラクター兼任**: ハヤアシがおすすめ（計算の見本を見せやすい）\n- **計算を「一緒にやる」**: 子どもに「じゃあ300×2は？」と一つずつ{聞|き}ながら進める\n- **ワンダー園長を演じる**: 「じいちゃんのトロフィーを見つけてくれ〜！」と盛り上げる\n\n#### 子どもの思考を引き出す声かけ例\n\n| 場面 | 声かけ |\n|---|---|\n| 地図を見せたとき | 「事務所からいちばん遠いのはどこ？ いちばん近いのは？」 |\n| 速さデータを見せたとき | 「ノンビリおばちゃんだけ速さが違うね。何が違う？」 |\n| 計算を始めるとき | 「まずハヤアシから計算してみよう。300mの往復は何m？」 |\n| 犯人が分かったとき | 「カケダシは20分もいなかったのに、往復10分で済む。残りの10分で何ができる？」 |\n| 解決編の後 | 「計算で犯人を見つけたね！ 算数ってこういうときにも使えるんだよ」 |\n\n---\n\n### {授業|じゅぎょう}用（45分版）の場合\n\n| 時間 | 内容 |\n|---|---|\n| 0:00-0:05 | 導入＋「速さ×時間＝距離」の復習 |\n| 0:05-0:10 | 共通情報・キャラクターシート配布＋読む時間 |\n| 0:10-0:22 | ステップ1：調査＋計算（全員が計算表を埋めるまで）|\n| 0:22-0:32 | ステップ2：計算会議（0:27ごろに証拠カード5）|\n| 0:32-0:38 | ステップ3：推理発表＋投票 |\n| 0:38-0:45 | 解決編＋チャレンジ問題＋振り返り |\n\n**{評価|ひょうか}ポイント（教師向け）:**\n- 「速さ×時間＝距離」の公式を正しく適用できたか\n- 往復距離の概念を理解し、計算に反映できたか\n- 複数の計算結果を比較し、論理的に結論を導けたか\n- 歩数計データ（歩数×歩幅＝距離）の計算ができたか\n\n**教科書との接続:**\n- 小5「速さ」の単元の**まとめ・応用**として最適\n- 小6の「比」「割合」の単元とも接続可能（速さの比較）\n- 「算数が日常で役立つ」実感を持たせる体験型教材\n\n**差別化ポイント:**\n- 従来の「速さの文章題」は抽象的で退屈になりがち\n- このゲームは「犯人を捕まえるために計算する」という動機がある\n- 「計算しないと犯人が分からない」→ 算数の必要性を体感\n- グループで計算結果を共有 → 「教え合い」が自然に発生\n",
  "discussionGuide": "",
  "killerQuestions": [],
  "challengeSection": "### チャレンジ問題（やってみよう！）\n\n#### 問題1\nもしカケダシの歩く速さが 80m/分 だったら、往復にかかる時間は何分？\n犯行はまだ可能？\n\n> ヒント: 1000m÷80m/分＝？分\n\n#### 問題2\nもしお化け屋敷が事務所から **1200m** の場所にあったら、\nカケダシは20分で往復できる？\n\n> ヒント: 1200×2÷100＝？分\n\n#### 問題3\nノンビリおばちゃんの空白時間が**10分**だったら、\nおばちゃんは事務所を往復できた？\n\n> ヒント: 400m÷50m/分＝？分\n\n---\n\n### チャレンジ問題の答え\n\n**問題1:** 1000÷80＝**12.5分**。空白20分＞12.5分なので、まだ犯行可能！\n**問題2:** 1200×2＝2400m。2400÷100＝**24分**。空白20分＜24分なので往復できない！\n**問題3:** 400÷50＝**8分**。空白10分＞8分なので往復できる！（おばちゃんも容疑者に！）\n\n**数字が1つ変わるだけで、犯人が変わることもある。だから計算は{正確|せいかく}に！**",
  "thumbnailUrl": "/images/math-01/thumb.webp"
}